{"UserIterationCapacity": {
    "_rallyAPIMajor": "2",
    "_rallyAPIMinor": "0",
    "_ref": "/slm/webservice/v2.0/useriterationcapacity/35908780",
    "_refObjectUUID": "94aaaa39-6e76-485f-abec-4d7b2fd64ac2",
    "_objectVersion": "1",
    "CreationDate": "2017-03-09T16:07:22.576Z",
    "_CreatedAt": "Mar 9",
    "ObjectID": 35908780,
    "VersionId": "1",
    "Subscription":     {
        "_rallyAPIMajor": "2",
        "_rallyAPIMinor": "0",
        "_ref": "/slm/webservice/v2.0/subscription/5104",
        "_refObjectUUID": "8edcc979-ce87-48f7-b129-699a393f58d8",
        "_refObjectName": "raytheon_az_-163",
        "_type": "Subscription"
    },
    "Workspace":     {
        "_rallyAPIMajor": "2",
        "_rallyAPIMinor": "0",
        "_ref": "/slm/webservice/v2.0/workspace/35545775",
        "_refObjectUUID": "18aa1d93-8bed-4a17-9d78-280593283b1f",
        "_refObjectName": "Business_Integration",
        "_type": "Workspace"
    },
    "Capacity": 128,
    "Iteration":     {
        "_rallyAPIMajor": "2",
        "_rallyAPIMinor": "0",
        "_ref": "/slm/webservice/v2.0/iteration/35906852",
        "_refObjectUUID": "4b360115-577d-41cd-83fe-f37c2e4e7fee",
        "_refObjectName": "Sprint Mar (03/13-04/15)",
        "_type": "Iteration"
    },
    "Load": 0.5625,
    "Project":     {
        "_rallyAPIMajor": "2",
        "_rallyAPIMinor": "0",
        "_ref": "/slm/webservice/v2.0/project/35743125",
        "_refObjectUUID": "fe437444-dbc8-4c07-a3bb-4a8d0100fa01",
        "_refObjectName": "CFM Data & Reporting",
        "_type": "Project"
    },
    "TaskEstimates": 72,
    "User":     {
        "_rallyAPIMajor": "2",
        "_rallyAPIMinor": "0",
        "_ref": "/slm/webservice/v2.0/user/35907379",
        "_refObjectUUID": "29f6f9f2-9aa5-4b9c-b0f1-68f3f875fee1",
        "_refObjectName": "Mark B",
        "_type": "User"
    },
    "Errors": [],
    "Warnings": []
}}