{"Iteration":{"_rallyAPIMajor":"2","_rallyAPIMinor":"0","_ref":"/slm/webservice/v2.0/iteration/35367483","_refObjectUUID":"b31bbc77-13b6-4a13-9e97-86a5624abbb8","_objectVersion":"1","_refObjectName":"Sprint 4","CreationDate":"2016-11-03T21:23:49.610Z","_CreatedAt":"Nov 3, 2016","ObjectID":35367483,"VersionId":"1","Subscription":{"_rallyAPIMajor":"2","_rallyAPIMinor":"0","_ref":"/slm/webservice/v2.0/subscription/5104","_refObjectUUID":"8edcc979-ce87-48f7-b129-699a393f58d8","_refObjectName":"raytheon_az_-163","_type":"Subscription"},"Workspace":{"_rallyAPIMajor":"2","_rallyAPIMinor":"0","_ref":"/slm/webservice/v2.0/workspace/69587","_refObjectUUID":"59391212-ec86-42b1-a315-b881f4b94958","_refObjectName":"BSD Workspace","_type":"Workspace"},"EndDate":"2017-01-18T06:59:59.000Z","Name":"Sprint 4","Notes":"","PlanEstimate":21,"PlannedVelocity":null,"Project":{"_rallyAPIMajor":"2","_rallyAPIMinor":"0","_ref":"/slm/webservice/v2.0/project/35271257","_refObjectUUID":"3e899738-85c6-41b3-8437-b38f8811b0da","_refObjectName":"AVO / AMS Enhancements","_type":"Project"},"RevisionHistory":{"_rallyAPIMajor":"2","_rallyAPIMinor":"0","_ref":"/slm/webservice/v2.0/revisionhistory/35367485","_refObjectUUID":"bbb0fcb9-fa04-4167-8ffa-a6f1b5dc12a2","_type":"RevisionHistory"},"StartDate":"2016-12-14T07:00:00.000Z","State":"Planning","TaskActualTotal":125.5,"TaskEstimateTotal":98,"TaskRemainingTotal":0,"Theme":"","UserIterationCapacities":{"_rallyAPIMajor":"2","_rallyAPIMinor":"0","_ref":"/slm/webservice/v2.0/Iteration/35367483/UserIterationCapacities","_type":"UserIterationCapacity","Count":3},"Errors":[],"Warnings":[]}}