{"HierarchicalRequirement": {
    "_rallyAPIMajor": "2",
    "_rallyAPIMinor": "0",
    "_ref": "/slm/webservice/v2.0/hierarchicalrequirement/35736487",
    "_refObjectUUID": "be93cdc0-9b05-4b44-b801-7191e2fa906e",
    "_objectVersion": "7",
    "_refObjectName": "upload Mocas report",
    "CreationDate": "2017-02-22T00:39:43.305Z",
    "_CreatedAt": "Feb 21",
    "ObjectID": 35736487,
    "VersionId": "7",
    "Subscription":     {
        "_rallyAPIMajor": "2",
        "_rallyAPIMinor": "0",
        "_ref": "/slm/webservice/v2.0/subscription/5104",
        "_refObjectUUID": "8edcc979-ce87-48f7-b129-699a393f58d8",
        "_refObjectName": "raytheon_az_-163",
        "_type": "Subscription"
    },
    "Workspace":     {
        "_rallyAPIMajor": "2",
        "_rallyAPIMinor": "0",
        "_ref": "/slm/webservice/v2.0/workspace/35545775",
        "_refObjectUUID": "18aa1d93-8bed-4a17-9d78-280593283b1f",
        "_refObjectName": "Business_Integration",
        "_type": "Workspace"
    },
    "Changesets":     {
        "_rallyAPIMajor": "2",
        "_rallyAPIMinor": "0",
        "_ref": "/slm/webservice/v2.0/HierarchicalRequirement/35736487/Changesets",
        "_type": "Changeset",
        "Count": 0
    },
    "Description": "<p>as ____ I need to manually upload the Mocas report so that ______________<\/p><p><br /><\/p><p>Per Cheryl Heath, We do not need to pull this data into the database, it is a link to the rshare upload.<\/p>",
    "Discussion":     {
        "_rallyAPIMajor": "2",
        "_rallyAPIMinor": "0",
        "_ref": "/slm/webservice/v2.0/HierarchicalRequirement/35736487/Discussion",
        "_type": "ConversationPost",
        "Count": 0
    },
    "DisplayColor": null,
    "Expedite": false,
    "FormattedID": "US80",
    "LastUpdateDate": "2017-03-10T20:51:16.482Z",
    "LatestDiscussionAgeInMinutes": null,
    "Milestones":     {
        "_rallyAPIMajor": "2",
        "_rallyAPIMinor": "0",
        "_ref": "/slm/webservice/v2.0/HierarchicalRequirement/35736487/Milestones",
        "_type": "Milestone",
        "_tagsNameArray": [],
        "Count": 0
    },
    "Name": "upload Mocas report",
    "Notes": "<p>3/8/2017 email from Cheryl Heath:<\/p><p><font face=\"Times New Roman\" size=\"3\">  <\/font><span style=\"color: rgb(31, 73, 125); font-family:\">Just to clarify, this is a DCMA report. They have now put an encryption on it.<\/span><\/p><p><font face=\"Times New Roman\" size=\"3\">  <\/font><span style=\"color: rgb(31, 73, 125); font-family:\">We get an email with the report directly from DCMA and I am good with that. There were other individuals who felt it would be nice to have access to it. Frankly, I don’t believe it should be part of the database. <\/span><\/p><p><font face=\"Times New Roman\" size=\"3\">  <\/font>--------------------<br /><\/p>",
    "Owner": null,
    "Project":     {
        "_rallyAPIMajor": "2",
        "_rallyAPIMinor": "0",
        "_ref": "/slm/webservice/v2.0/project/35723837",
        "_refObjectUUID": "d2825bcd-6755-4bb6-ab24-65e423f70678",
        "_refObjectName": "PRS  (PPM 287099)",
        "_type": "Project"
    },
    "Ready": false,
    "RevisionHistory":     {
        "_rallyAPIMajor": "2",
        "_rallyAPIMinor": "0",
        "_ref": "/slm/webservice/v2.0/revisionhistory/35736488",
        "_refObjectUUID": "65446187-a2c2-4192-8951-5c237395b177",
        "_type": "RevisionHistory"
    },
    "Tags":     {
        "_rallyAPIMajor": "2",
        "_rallyAPIMinor": "0",
        "_ref": "/slm/webservice/v2.0/HierarchicalRequirement/35736487/Tags",
        "_type": "Tag",
        "_tagsNameArray": [],
        "Count": 0
    },
    "LastBuild": null,
    "LastRun": null,
    "PassingTestCaseCount": 0,
    "ScheduleState": "Defined",
    "TestCaseCount": 0,
    "Attachments":     {
        "_rallyAPIMajor": "2",
        "_rallyAPIMinor": "0",
        "_ref": "/slm/webservice/v2.0/HierarchicalRequirement/35736487/Attachments",
        "_type": "Attachment",
        "Count": 0
    },
    "Package": null,
    "AcceptedDate": null,
    "Blocked": false,
    "BlockedReason": null,
    "Blocker": null,
    "Children":     {
        "_rallyAPIMajor": "2",
        "_rallyAPIMinor": "0",
        "_ref": "/slm/webservice/v2.0/HierarchicalRequirement/35736487/Children",
        "_type": "HierarchicalRequirement",
        "Count": 0
    },
    "DefectStatus": "NONE",
    "Defects":     {
        "_rallyAPIMajor": "2",
        "_rallyAPIMinor": "0",
        "_ref": "/slm/webservice/v2.0/HierarchicalRequirement/35736487/Defects",
        "_type": "Defect",
        "Count": 0
    },
    "DirectChildrenCount": 0,
    "DragAndDropRank": "O~~~h8O~~~~~~~~~~~~~~~~~~~~~~~~~~~~~~~~~~~~~~~~~~~~~~~~~~~~~~~~~",
    "HasParent": true,
    "InProgressDate": null,
    "Iteration": null,
    "Parent":     {
        "_rallyAPIMajor": "2",
        "_rallyAPIMinor": "0",
        "_ref": "/slm/webservice/v2.0/hierarchicalrequirement/35735672",
        "_refObjectUUID": "1a34b654-fce0-4996-86a9-5786d145f708",
        "_refObjectName": "Data Acquisition & Preparation",
        "_type": "HierarchicalRequirement"
    },
    "PlanEstimate": null,
    "Predecessors":     {
        "_rallyAPIMajor": "2",
        "_rallyAPIMinor": "0",
        "_ref": "/slm/webservice/v2.0/HierarchicalRequirement/35736487/Predecessors",
        "_type": "HierarchicalRequirement",
        "Count": 0
    },
    "Recycled": false,
    "Release": null,
    "Successors":     {
        "_rallyAPIMajor": "2",
        "_rallyAPIMinor": "0",
        "_ref": "/slm/webservice/v2.0/HierarchicalRequirement/35736487/Successors",
        "_type": "HierarchicalRequirement",
        "Count": 0
    },
    "TaskActualTotal": 0,
    "TaskEstimateTotal": 0,
    "TaskRemainingTotal": 0,
    "TaskStatus": "NONE",
    "Tasks":     {
        "_rallyAPIMajor": "2",
        "_rallyAPIMinor": "0",
        "_ref": "/slm/webservice/v2.0/HierarchicalRequirement/35736487/Tasks",
        "_type": "Task",
        "Count": 0
    },
    "TestCaseStatus": "NONE",
    "TestCases":     {
        "_rallyAPIMajor": "2",
        "_rallyAPIMinor": "0",
        "_ref": "/slm/webservice/v2.0/HierarchicalRequirement/35736487/TestCases",
        "_type": "TestCase",
        "Count": 0
    },
    "c_BizValue": null,
    "Feature": null,
    "PortfolioItem": null,
    "Errors": [],
    "Warnings": []
}}