{"HierarchicalRequirement": {
    "_rallyAPIMajor": "2",
    "_rallyAPIMinor": "0",
    "_ref": "/slm/webservice/v2.0/hierarchicalrequirement/36032485",
    "_refObjectUUID": "f000270d-06d9-4dbc-a6d7-46666c2522da",
    "_objectVersion": "12",
    "_refObjectName": "Footer",
    "CreationDate": "2017-04-19T18:03:04.072Z",
    "_CreatedAt": "Apr 19",
    "ObjectID": 36032485,
    "VersionId": "12",
    "Subscription":     {
        "_rallyAPIMajor": "2",
        "_rallyAPIMinor": "0",
        "_ref": "/slm/webservice/v2.0/subscription/5104",
        "_refObjectUUID": "8edcc979-ce87-48f7-b129-699a393f58d8",
        "_refObjectName": "raytheon_az_-163",
        "_type": "Subscription"
    },
    "Workspace":     {
        "_rallyAPIMajor": "2",
        "_rallyAPIMinor": "0",
        "_ref": "/slm/webservice/v2.0/workspace/35545775",
        "_refObjectUUID": "18aa1d93-8bed-4a17-9d78-280593283b1f",
        "_refObjectName": "Business_Integration",
        "_type": "Workspace"
    },
    "Changesets":     {
        "_rallyAPIMajor": "2",
        "_rallyAPIMinor": "0",
        "_ref": "/slm/webservice/v2.0/HierarchicalRequirement/36032485/Changesets",
        "_type": "Changeset",
        "Count": 0
    },
    "Description": "",
    "Discussion":     {
        "_rallyAPIMajor": "2",
        "_rallyAPIMinor": "0",
        "_ref": "/slm/webservice/v2.0/HierarchicalRequirement/36032485/Discussion",
        "_type": "ConversationPost",
        "Count": 0
    },
    "DisplayColor": null,
    "Expedite": false,
    "FormattedID": "US1129",
    "LastUpdateDate": "2017-05-08T20:47:53.942Z",
    "LatestDiscussionAgeInMinutes": null,
    "Milestones":     {
        "_rallyAPIMajor": "2",
        "_rallyAPIMinor": "0",
        "_ref": "/slm/webservice/v2.0/HierarchicalRequirement/36032485/Milestones",
        "_type": "Milestone",
        "_tagsNameArray": [],
        "Count": 0
    },
    "Name": "Footer",
    "Notes": "",
    "Owner": null,
    "Project":     {
        "_rallyAPIMajor": "2",
        "_rallyAPIMinor": "0",
        "_ref": "/slm/webservice/v2.0/project/35808274",
        "_refObjectUUID": "84d05999-e6e8-4e38-a921-d49c07cad45a",
        "_refObjectName": "mSTAT",
        "_type": "Project"
    },
    "Ready": false,
    "RevisionHistory":     {
        "_rallyAPIMajor": "2",
        "_rallyAPIMinor": "0",
        "_ref": "/slm/webservice/v2.0/revisionhistory/36032486",
        "_refObjectUUID": "1b0cc9b7-f9e8-41b6-ab22-1c92c86e870e",
        "_type": "RevisionHistory"
    },
    "Tags":     {
        "_rallyAPIMajor": "2",
        "_rallyAPIMinor": "0",
        "_ref": "/slm/webservice/v2.0/HierarchicalRequirement/36032485/Tags",
        "_type": "Tag",
        "_tagsNameArray": [],
        "Count": 0
    },
    "LastBuild": null,
    "LastRun": null,
    "PassingTestCaseCount": 0,
    "ScheduleState": "Accepted",
    "TestCaseCount": 0,
    "Attachments":     {
        "_rallyAPIMajor": "2",
        "_rallyAPIMinor": "0",
        "_ref": "/slm/webservice/v2.0/HierarchicalRequirement/36032485/Attachments",
        "_type": "Attachment",
        "Count": 0
    },
    "Package": null,
    "AcceptedDate": "2017-05-08T20:47:53.904Z",
    "Blocked": false,
    "BlockedReason": null,
    "Blocker": null,
    "Children":     {
        "_rallyAPIMajor": "2",
        "_rallyAPIMinor": "0",
        "_ref": "/slm/webservice/v2.0/HierarchicalRequirement/36032485/Children",
        "_type": "HierarchicalRequirement",
        "Count": 1
    },
    "DefectStatus": null,
    "Defects":     {
        "_rallyAPIMajor": "2",
        "_rallyAPIMinor": "0",
        "_ref": "/slm/webservice/v2.0/HierarchicalRequirement/36032485/Defects",
        "_type": "Defect",
        "Count": 0
    },
    "DirectChildrenCount": 1,
    "DragAndDropRank": "O~~xlmD8O~~~~~~~~~~~~~~~~~~~~~~~~~~~~~~~~~~~~~~~~~~~~~~~~~~~~~~~",
    "HasParent": false,
    "InProgressDate": "2017-04-21T15:30:40.362Z",
    "Iteration": null,
    "Parent": null,
    "PlanEstimate": 1,
    "Predecessors":     {
        "_rallyAPIMajor": "2",
        "_rallyAPIMinor": "0",
        "_ref": "/slm/webservice/v2.0/HierarchicalRequirement/36032485/Predecessors",
        "_type": "HierarchicalRequirement",
        "Count": 0
    },
    "Recycled": false,
    "Release": null,
    "Successors":     {
        "_rallyAPIMajor": "2",
        "_rallyAPIMinor": "0",
        "_ref": "/slm/webservice/v2.0/HierarchicalRequirement/36032485/Successors",
        "_type": "HierarchicalRequirement",
        "Count": 0
    },
    "TaskActualTotal": 0,
    "TaskEstimateTotal": 0,
    "TaskRemainingTotal": 0,
    "TaskStatus": null,
    "Tasks":     {
        "_rallyAPIMajor": "2",
        "_rallyAPIMinor": "0",
        "_ref": "/slm/webservice/v2.0/HierarchicalRequirement/36032485/Tasks",
        "_type": "Task",
        "Count": 0
    },
    "TestCaseStatus": null,
    "TestCases":     {
        "_rallyAPIMajor": "2",
        "_rallyAPIMinor": "0",
        "_ref": "/slm/webservice/v2.0/HierarchicalRequirement/36032485/TestCases",
        "_type": "TestCase",
        "Count": 0
    },
    "c_BizValue": null,
    "Feature": null,
    "PortfolioItem": null,
    "Errors": [],
    "Warnings": []
}}