{"HierarchicalRequirement": {
    "_rallyAPIMajor": "2",
    "_rallyAPIMinor": "0",
    "_ref": "/slm/webservice/v2.0/hierarchicalrequirement/36062316",
    "_refObjectUUID": "1d818c5e-f942-46c5-8ba0-bc0bac0d198a",
    "_objectVersion": "2",
    "_refObjectName": "[Unfinished] Analysis - GFM Data - BA",
    "CreationDate": "2017-05-01T15:31:06.951Z",
    "_CreatedAt": "May 1",
    "ObjectID": 36062316,
    "VersionId": "2",
    "Subscription":     {
        "_rallyAPIMajor": "2",
        "_rallyAPIMinor": "0",
        "_ref": "/slm/webservice/v2.0/subscription/5104",
        "_refObjectUUID": "8edcc979-ce87-48f7-b129-699a393f58d8",
        "_refObjectName": "raytheon_az_-163",
        "_type": "Subscription"
    },
    "Workspace":     {
        "_rallyAPIMajor": "2",
        "_rallyAPIMinor": "0",
        "_ref": "/slm/webservice/v2.0/workspace/35545775",
        "_refObjectUUID": "18aa1d93-8bed-4a17-9d78-280593283b1f",
        "_refObjectName": "Business_Integration",
        "_type": "Workspace"
    },
    "Changesets":     {
        "_rallyAPIMajor": "2",
        "_rallyAPIMinor": "0",
        "_ref": "/slm/webservice/v2.0/HierarchicalRequirement/36062316/Changesets",
        "_type": "Changeset",
        "Count": 0
    },
    "Description": "",
    "Discussion":     {
        "_rallyAPIMajor": "2",
        "_rallyAPIMinor": "0",
        "_ref": "/slm/webservice/v2.0/HierarchicalRequirement/36062316/Discussion",
        "_type": "ConversationPost",
        "Count": 0
    },
    "DisplayColor": null,
    "Expedite": false,
    "FormattedID": "US1167",
    "LastUpdateDate": "2017-05-01T15:31:12.909Z",
    "LatestDiscussionAgeInMinutes": null,
    "Milestones":     {
        "_rallyAPIMajor": "2",
        "_rallyAPIMinor": "0",
        "_ref": "/slm/webservice/v2.0/HierarchicalRequirement/36062316/Milestones",
        "_type": "Milestone",
        "_tagsNameArray": [],
        "Count": 0
    },
    "Name": "[Unfinished] Analysis - GFM Data - BA",
    "Notes": "",
    "Owner":     {
        "_rallyAPIMajor": "2",
        "_rallyAPIMinor": "0",
        "_ref": "/slm/webservice/v2.0/user/69986",
        "_refObjectUUID": "d7eeb7a5-bce9-4aa3-8d3a-a5a0e7fbeba9",
        "_refObjectName": "Brian Kristofitz",
        "_type": "User"
    },
    "Project":     {
        "_rallyAPIMajor": "2",
        "_rallyAPIMinor": "0",
        "_ref": "/slm/webservice/v2.0/project/35734993",
        "_refObjectUUID": "b0797f7e-f500-4649-b56f-8a8c66a1fa7a",
        "_refObjectName": "PRS Data & Reporting",
        "_type": "Project"
    },
    "Ready": false,
    "RevisionHistory":     {
        "_rallyAPIMajor": "2",
        "_rallyAPIMinor": "0",
        "_ref": "/slm/webservice/v2.0/revisionhistory/36062317",
        "_refObjectUUID": "755d645c-f069-41a1-aee8-7abbc8d18757",
        "_type": "RevisionHistory"
    },
    "Tags":     {
        "_rallyAPIMajor": "2",
        "_rallyAPIMinor": "0",
        "_ref": "/slm/webservice/v2.0/HierarchicalRequirement/36062316/Tags",
        "_type": "Tag",
        "_tagsNameArray": [],
        "Count": 0
    },
    "LastBuild": null,
    "LastRun": null,
    "PassingTestCaseCount": 0,
    "ScheduleState": "Completed",
    "TestCaseCount": 0,
    "Attachments":     {
        "_rallyAPIMajor": "2",
        "_rallyAPIMinor": "0",
        "_ref": "/slm/webservice/v2.0/HierarchicalRequirement/36062316/Attachments",
        "_type": "Attachment",
        "Count": 0
    },
    "Package": null,
    "AcceptedDate": null,
    "Blocked": false,
    "BlockedReason": null,
    "Blocker": null,
    "Children":     {
        "_rallyAPIMajor": "2",
        "_rallyAPIMinor": "0",
        "_ref": "/slm/webservice/v2.0/HierarchicalRequirement/36062316/Children",
        "_type": "HierarchicalRequirement",
        "Count": 0
    },
    "DefectStatus": "NONE",
    "Defects":     {
        "_rallyAPIMajor": "2",
        "_rallyAPIMinor": "0",
        "_ref": "/slm/webservice/v2.0/HierarchicalRequirement/36062316/Defects",
        "_type": "Defect",
        "Count": 0
    },
    "DirectChildrenCount": 0,
    "DragAndDropRank": "O~~xR~~~~~~~~~~~~~~~~~~~~~~~~~~~~~~~~~~~~~~~~~~~~~~~~~~~~~~~~~~~",
    "HasParent": true,
    "InProgressDate": "2017-05-01T15:31:06.974Z",
    "Iteration":     {
        "_rallyAPIMajor": "2",
        "_rallyAPIMinor": "0",
        "_ref": "/slm/webservice/v2.0/iteration/35807096",
        "_refObjectUUID": "bda1bd3f-a9ee-4380-b1ca-f08b9d9af1f8",
        "_refObjectName": "Sprint 2",
        "_type": "Iteration"
    },
    "Parent":     {
        "_rallyAPIMajor": "2",
        "_rallyAPIMinor": "0",
        "_ref": "/slm/webservice/v2.0/hierarchicalrequirement/36062206",
        "_refObjectUUID": "011a54b3-e884-49be-aaee-9ef46c052c02",
        "_refObjectName": "Analysis - GFM Data - BA",
        "_type": "HierarchicalRequirement"
    },
    "PlanEstimate": 5,
    "Predecessors":     {
        "_rallyAPIMajor": "2",
        "_rallyAPIMinor": "0",
        "_ref": "/slm/webservice/v2.0/HierarchicalRequirement/36062316/Predecessors",
        "_type": "HierarchicalRequirement",
        "Count": 0
    },
    "Recycled": false,
    "Release":     {
        "_rallyAPIMajor": "2",
        "_rallyAPIMinor": "0",
        "_ref": "/slm/webservice/v2.0/release/35735004",
        "_refObjectUUID": "286ef592-e5b0-4228-96d1-9e6c79c1e822",
        "_refObjectName": "Dec 2017",
        "_type": "Release"
    },
    "Successors":     {
        "_rallyAPIMajor": "2",
        "_rallyAPIMinor": "0",
        "_ref": "/slm/webservice/v2.0/HierarchicalRequirement/36062316/Successors",
        "_type": "HierarchicalRequirement",
        "Count": 0
    },
    "TaskActualTotal": 0,
    "TaskEstimateTotal": 0,
    "TaskRemainingTotal": 0,
    "TaskStatus": "NONE",
    "Tasks":     {
        "_rallyAPIMajor": "2",
        "_rallyAPIMinor": "0",
        "_ref": "/slm/webservice/v2.0/HierarchicalRequirement/36062316/Tasks",
        "_type": "Task",
        "Count": 0
    },
    "TestCaseStatus": "NONE",
    "TestCases":     {
        "_rallyAPIMajor": "2",
        "_rallyAPIMinor": "0",
        "_ref": "/slm/webservice/v2.0/HierarchicalRequirement/36062316/TestCases",
        "_type": "TestCase",
        "Count": 0
    },
    "c_BizValue": null,
    "Feature": null,
    "PortfolioItem": null,
    "Errors": [],
    "Warnings": []
}}