{"QueryResult": {
    "_rallyAPIMajor": "2",
    "_rallyAPIMinor": "0",
    "Errors": [],
    "Warnings": [],
    "TotalResultCount": 7,
    "StartIndex": 1,
    "PageSize": 20,
    "Results":     [
                {
            "_rallyAPIMajor": "2",
            "_rallyAPIMinor": "0",
            "_ref": "/slm/webservice/v2.0/hierarchicalrequirement/34294957",
            "_refObjectUUID": "e4c37b63-27de-4edb-8d72-a4d3172dd780",
            "_objectVersion": "78",
            "_refObjectName": "SubFeature: Report - Create PDF",
            "CreationDate": "2016-03-09T16:18:27.407Z",
            "_CreatedAt": "Mar 9, 2016",
            "ObjectID": 34294957,
            "VersionId": "78",
            "Subscription":             {
                "_rallyAPIMajor": "2",
                "_rallyAPIMinor": "0",
                "_ref": "/slm/webservice/v2.0/subscription/5104",
                "_refObjectUUID": "8edcc979-ce87-48f7-b129-699a393f58d8",
                "_refObjectName": "raytheon_az_-163",
                "_type": "Subscription"
            },
            "Workspace":             {
                "_rallyAPIMajor": "2",
                "_rallyAPIMinor": "0",
                "_ref": "/slm/webservice/v2.0/workspace/69587",
                "_refObjectUUID": "59391212-ec86-42b1-a315-b881f4b94958",
                "_refObjectName": "BSD Workspace",
                "_type": "Workspace"
            },
            "Changesets":             {
                "_rallyAPIMajor": "2",
                "_rallyAPIMinor": "0",
                "_ref": "/slm/webservice/v2.0/HierarchicalRequirement/34294957/Changesets",
                "_type": "Changeset",
                "Count": 0
            },
            "Description": "<p>•Report - Save as PDF<br />&nbsp;◦Rtn marking<br />&nbsp;◦Date marking<br />&nbsp;◦Email pdf to yourself - no need to cc<br />•Available for mobile device users<br />•Ability to preview the pdf prior to emailing it.<\/p><p>•PDF: Report Option: Show/Don't Show Sources<br />&nbsp;◦Bibliography at the bottom (page break) with an indicator on the field value to visually display that the field has been changed.<\/p><p><br />• Report Option: Subscribe to data changes for this report run. If someone changes the data in a report that ran, the subscriber would be notified that they need to re-run the report.<br />&nbsp;• Keeps users engaged and confident with the PCD that data is getting updated<br /><\/p>",
            "Discussion":             {
                "_rallyAPIMajor": "2",
                "_rallyAPIMinor": "0",
                "_ref": "/slm/webservice/v2.0/HierarchicalRequirement/34294957/Discussion",
                "_type": "ConversationPost",
                "Count": 0
            },
            "DisplayColor": null,
            "Expedite": false,
            "FormattedID": "US10598",
            "LastUpdateDate": "2016-06-23T18:50:07.639Z",
            "LatestDiscussionAgeInMinutes": null,
            "Milestones":             {
                "_rallyAPIMajor": "2",
                "_rallyAPIMinor": "0",
                "_ref": "/slm/webservice/v2.0/HierarchicalRequirement/34294957/Milestones",
                "_type": "Milestone",
                "_tagsNameArray": [],
                "Count": 0
            },
            "Name": "SubFeature: Report - Create PDF",
            "Notes": "",
            "Owner":             {
                "_rallyAPIMajor": "2",
                "_rallyAPIMinor": "0",
                "_ref": "/slm/webservice/v2.0/user/33607268",
                "_refObjectUUID": "8b51ad49-d060-41bf-b4d0-918a2466ee43",
                "_refObjectName": "Brad Isbell",
                "_type": "User"
            },
            "Project":             {
                "_rallyAPIMajor": "2",
                "_rallyAPIMinor": "0",
                "_ref": "/slm/webservice/v2.0/project/34279769",
                "_refObjectUUID": "82b32c7c-0e75-4735-a5ba-79099094b552",
                "_refObjectName": "PCD",
                "_type": "Project"
            },
            "Ready": false,
            "RevisionHistory":             {
                "_rallyAPIMajor": "2",
                "_rallyAPIMinor": "0",
                "_ref": "/slm/webservice/v2.0/revisionhistory/34294958",
                "_refObjectUUID": "bb5a684a-829b-44bf-9600-17f62621071b",
                "_type": "RevisionHistory"
            },
            "Tags":             {
                "_rallyAPIMajor": "2",
                "_rallyAPIMinor": "0",
                "_ref": "/slm/webservice/v2.0/HierarchicalRequirement/34294957/Tags",
                "_type": "Tag",
                "_tagsNameArray": [],
                "Count": 0
            },
            "LastBuild": null,
            "LastRun": null,
            "PassingTestCaseCount": 0,
            "ScheduleState": "Accepted",
            "TestCaseCount": 0,
            "Attachments":             {
                "_rallyAPIMajor": "2",
                "_rallyAPIMinor": "0",
                "_ref": "/slm/webservice/v2.0/HierarchicalRequirement/34294957/Attachments",
                "_type": "Attachment",
                "Count": 0
            },
            "Package": null,
            "AcceptedDate": "2016-06-23T18:50:07.561Z",
            "Blocked": false,
            "BlockedReason": null,
            "Blocker": null,
            "Children":             {
                "_rallyAPIMajor": "2",
                "_rallyAPIMinor": "0",
                "_ref": "/slm/webservice/v2.0/HierarchicalRequirement/34294957/Children",
                "_type": "HierarchicalRequirement",
                "Count": 2
            },
            "DefectStatus": null,
            "Defects":             {
                "_rallyAPIMajor": "2",
                "_rallyAPIMinor": "0",
                "_ref": "/slm/webservice/v2.0/HierarchicalRequirement/34294957/Defects",
                "_type": "Defect",
                "Count": 0
            },
            "DirectChildrenCount": 2,
            "DragAndDropRank": "P!!VM~~~~~~~~~~~~~~~~~~~~~~~~~~~~~~~~~~~~~~~~~~~~~~~~~~~~~~~~~~~",
            "HasParent": true,
            "InProgressDate": "2016-05-09T18:26:31.598Z",
            "Iteration": null,
            "Parent":             {
                "_rallyAPIMajor": "2",
                "_rallyAPIMinor": "0",
                "_ref": "/slm/webservice/v2.0/hierarchicalrequirement/34294911",
                "_refObjectUUID": "5f75d092-a0e4-4494-802f-7abc1f6d17b8",
                "_refObjectName": "Feature: Generate Report",
                "_type": "HierarchicalRequirement"
            },
            "PlanEstimate": 18,
            "Predecessors":             {
                "_rallyAPIMajor": "2",
                "_rallyAPIMinor": "0",
                "_ref": "/slm/webservice/v2.0/HierarchicalRequirement/34294957/Predecessors",
                "_type": "HierarchicalRequirement",
                "Count": 0
            },
            "Recycled": false,
            "Release": null,
            "Successors":             {
                "_rallyAPIMajor": "2",
                "_rallyAPIMinor": "0",
                "_ref": "/slm/webservice/v2.0/HierarchicalRequirement/34294957/Successors",
                "_type": "HierarchicalRequirement",
                "Count": 0
            },
            "TaskActualTotal": 61.75,
            "TaskEstimateTotal": 83,
            "TaskRemainingTotal": 0,
            "TaskStatus": null,
            "Tasks":             {
                "_rallyAPIMajor": "2",
                "_rallyAPIMinor": "0",
                "_ref": "/slm/webservice/v2.0/HierarchicalRequirement/34294957/Tasks",
                "_type": "Task",
                "Count": 0
            },
            "TestCaseStatus": null,
            "TestCases":             {
                "_rallyAPIMajor": "2",
                "_rallyAPIMinor": "0",
                "_ref": "/slm/webservice/v2.0/HierarchicalRequirement/34294957/TestCases",
                "_type": "TestCase",
                "Count": 0
            },
            "c_ACv4ReqID": null,
            "c_AISRequirementID": null,
            "c_ANTReqID": null,
            "c_BizValue": null,
            "c_CAPTSReqID": null,
            "c_COTSAISReqID": null,
            "c_CromaReqID": null,
            "c_EBinderReqID": null,
            "c_EcBinderReqID": null,
            "c_ETSCReqID": null,
            "Feature": null,
            "c_FRACASReqID": null,
            "c_HRRAReqID": null,
            "c_ITRRReqID": null,
            "c_MsfReqID": null,
            "c_NBIDCReqID": null,
            "c_NFDEReqID": null,
            "c_PARTSReqID": null,
            "c_PMRTReqID": null,
            "c_POAcceptanceCriteria": null,
            "PortfolioItem": null,
            "c_QCAttachments": null,
            "c_QCReqID": null,
            "c_QES2ReqID": null,
            "c_QES2ReqIDDELETED": null,
            "c_Qt2ReqID": null,
            "c_QT3ReqID": null,
            "c_RaMPReqID": null,
            "c_RfutureReqID": null,
            "c_RgemsReqID": null,
            "c_RISCATSReqID": null,
            "c_RLabsReqID": null,
            "c_SABSSReqID": null,
            "c_SabssReqIddelete": null,
            "c_SOCRReqID": null,
            "c_SRDReqID": null,
            "c_SUPSRSRqmtID": null,
            "c_SysReqID": null,
            "c_TandCReqIDCOTS": null,
            "c_TermsandConditionsReqID": null,
            "c_TripodReqID": null,
            "_type": "HierarchicalRequirement"
        },
                {
            "_rallyAPIMajor": "2",
            "_rallyAPIMinor": "0",
            "_ref": "/slm/webservice/v2.0/hierarchicalrequirement/34295018",
            "_refObjectUUID": "1948f27e-6792-46cb-ab67-6c22146c9888",
            "_objectVersion": "19",
            "_refObjectName": "SubFeature: Report - Create Excel/CSV",
            "CreationDate": "2016-03-09T16:18:39.582Z",
            "_CreatedAt": "Mar 9, 2016",
            "ObjectID": 34295018,
            "VersionId": "19",
            "Subscription":             {
                "_rallyAPIMajor": "2",
                "_rallyAPIMinor": "0",
                "_ref": "/slm/webservice/v2.0/subscription/5104",
                "_refObjectUUID": "8edcc979-ce87-48f7-b129-699a393f58d8",
                "_refObjectName": "raytheon_az_-163",
                "_type": "Subscription"
            },
            "Workspace":             {
                "_rallyAPIMajor": "2",
                "_rallyAPIMinor": "0",
                "_ref": "/slm/webservice/v2.0/workspace/69587",
                "_refObjectUUID": "59391212-ec86-42b1-a315-b881f4b94958",
                "_refObjectName": "BSD Workspace",
                "_type": "Workspace"
            },
            "Changesets":             {
                "_rallyAPIMajor": "2",
                "_rallyAPIMinor": "0",
                "_ref": "/slm/webservice/v2.0/HierarchicalRequirement/34295018/Changesets",
                "_type": "Changeset",
                "Count": 0
            },
            "Description": "Not available to mobile device users.",
            "Discussion":             {
                "_rallyAPIMajor": "2",
                "_rallyAPIMinor": "0",
                "_ref": "/slm/webservice/v2.0/HierarchicalRequirement/34295018/Discussion",
                "_type": "ConversationPost",
                "Count": 0
            },
            "DisplayColor": null,
            "Expedite": false,
            "FormattedID": "US10599",
            "LastUpdateDate": "2016-10-18T23:03:49.901Z",
            "LatestDiscussionAgeInMinutes": null,
            "Milestones":             {
                "_rallyAPIMajor": "2",
                "_rallyAPIMinor": "0",
                "_ref": "/slm/webservice/v2.0/HierarchicalRequirement/34295018/Milestones",
                "_type": "Milestone",
                "_tagsNameArray": [],
                "Count": 0
            },
            "Name": "SubFeature: Report - Create Excel/CSV",
            "Notes": "",
            "Owner":             {
                "_rallyAPIMajor": "2",
                "_rallyAPIMinor": "0",
                "_ref": "/slm/webservice/v2.0/user/33607268",
                "_refObjectUUID": "8b51ad49-d060-41bf-b4d0-918a2466ee43",
                "_refObjectName": "Brad Isbell",
                "_type": "User"
            },
            "Project":             {
                "_rallyAPIMajor": "2",
                "_rallyAPIMinor": "0",
                "_ref": "/slm/webservice/v2.0/project/34279769",
                "_refObjectUUID": "82b32c7c-0e75-4735-a5ba-79099094b552",
                "_refObjectName": "PCD",
                "_type": "Project"
            },
            "Ready": false,
            "RevisionHistory":             {
                "_rallyAPIMajor": "2",
                "_rallyAPIMinor": "0",
                "_ref": "/slm/webservice/v2.0/revisionhistory/34295019",
                "_refObjectUUID": "638fe0e4-185b-46f5-819d-9db966c4b0c6",
                "_type": "RevisionHistory"
            },
            "Tags":             {
                "_rallyAPIMajor": "2",
                "_rallyAPIMinor": "0",
                "_ref": "/slm/webservice/v2.0/HierarchicalRequirement/34295018/Tags",
                "_type": "Tag",
                "_tagsNameArray": [],
                "Count": 0
            },
            "LastBuild": null,
            "LastRun": null,
            "PassingTestCaseCount": 0,
            "ScheduleState": "Accepted",
            "TestCaseCount": 0,
            "Attachments":             {
                "_rallyAPIMajor": "2",
                "_rallyAPIMinor": "0",
                "_ref": "/slm/webservice/v2.0/HierarchicalRequirement/34295018/Attachments",
                "_type": "Attachment",
                "Count": 0
            },
            "Package": null,
            "AcceptedDate": "2016-10-18T23:03:49.825Z",
            "Blocked": false,
            "BlockedReason": null,
            "Blocker": null,
            "Children":             {
                "_rallyAPIMajor": "2",
                "_rallyAPIMinor": "0",
                "_ref": "/slm/webservice/v2.0/HierarchicalRequirement/34295018/Children",
                "_type": "HierarchicalRequirement",
                "Count": 1
            },
            "DefectStatus": null,
            "Defects":             {
                "_rallyAPIMajor": "2",
                "_rallyAPIMinor": "0",
                "_ref": "/slm/webservice/v2.0/HierarchicalRequirement/34295018/Defects",
                "_type": "Defect",
                "Count": 0
            },
            "DirectChildrenCount": 1,
            "DragAndDropRank": ",~~kD#h:SL3P865FG2[gP!!!!!!!!!!!!!!!!!!!!!!!!!!!!!!!!!!!!!!!!!!!",
            "HasParent": true,
            "InProgressDate": "2016-09-26T22:58:38.458Z",
            "Iteration": null,
            "Parent":             {
                "_rallyAPIMajor": "2",
                "_rallyAPIMinor": "0",
                "_ref": "/slm/webservice/v2.0/hierarchicalrequirement/34294911",
                "_refObjectUUID": "5f75d092-a0e4-4494-802f-7abc1f6d17b8",
                "_refObjectName": "Feature: Generate Report",
                "_type": "HierarchicalRequirement"
            },
            "PlanEstimate": 8,
            "Predecessors":             {
                "_rallyAPIMajor": "2",
                "_rallyAPIMinor": "0",
                "_ref": "/slm/webservice/v2.0/HierarchicalRequirement/34295018/Predecessors",
                "_type": "HierarchicalRequirement",
                "Count": 0
            },
            "Recycled": false,
            "Release": null,
            "Successors":             {
                "_rallyAPIMajor": "2",
                "_rallyAPIMinor": "0",
                "_ref": "/slm/webservice/v2.0/HierarchicalRequirement/34295018/Successors",
                "_type": "HierarchicalRequirement",
                "Count": 0
            },
            "TaskActualTotal": 8.5,
            "TaskEstimateTotal": 9,
            "TaskRemainingTotal": 0,
            "TaskStatus": null,
            "Tasks":             {
                "_rallyAPIMajor": "2",
                "_rallyAPIMinor": "0",
                "_ref": "/slm/webservice/v2.0/HierarchicalRequirement/34295018/Tasks",
                "_type": "Task",
                "Count": 0
            },
            "TestCaseStatus": null,
            "TestCases":             {
                "_rallyAPIMajor": "2",
                "_rallyAPIMinor": "0",
                "_ref": "/slm/webservice/v2.0/HierarchicalRequirement/34295018/TestCases",
                "_type": "TestCase",
                "Count": 0
            },
            "c_ACv4ReqID": null,
            "c_AISRequirementID": null,
            "c_ANTReqID": null,
            "c_BizValue": null,
            "c_CAPTSReqID": null,
            "c_COTSAISReqID": null,
            "c_CromaReqID": null,
            "c_EBinderReqID": null,
            "c_EcBinderReqID": null,
            "c_ETSCReqID": null,
            "Feature": null,
            "c_FRACASReqID": null,
            "c_HRRAReqID": null,
            "c_ITRRReqID": null,
            "c_MsfReqID": null,
            "c_NBIDCReqID": null,
            "c_NFDEReqID": null,
            "c_PARTSReqID": null,
            "c_PMRTReqID": null,
            "c_POAcceptanceCriteria": null,
            "PortfolioItem": null,
            "c_QCAttachments": null,
            "c_QCReqID": null,
            "c_QES2ReqID": null,
            "c_QES2ReqIDDELETED": null,
            "c_Qt2ReqID": null,
            "c_QT3ReqID": null,
            "c_RaMPReqID": null,
            "c_RfutureReqID": null,
            "c_RgemsReqID": null,
            "c_RISCATSReqID": null,
            "c_RLabsReqID": null,
            "c_SABSSReqID": null,
            "c_SabssReqIddelete": null,
            "c_SOCRReqID": null,
            "c_SRDReqID": null,
            "c_SUPSRSRqmtID": null,
            "c_SysReqID": null,
            "c_TandCReqIDCOTS": null,
            "c_TermsandConditionsReqID": null,
            "c_TripodReqID": null,
            "_type": "HierarchicalRequirement"
        },
                {
            "_rallyAPIMajor": "2",
            "_rallyAPIMinor": "0",
            "_ref": "/slm/webservice/v2.0/hierarchicalrequirement/34295131",
            "_refObjectUUID": "b852a8e1-ed25-4fc6-8112-61c9cc536bbc",
            "_objectVersion": "11",
            "_refObjectName": "SubFeature: Report - Create as Word document",
            "CreationDate": "2016-03-09T16:20:51.902Z",
            "_CreatedAt": "Mar 9, 2016",
            "ObjectID": 34295131,
            "VersionId": "11",
            "Subscription":             {
                "_rallyAPIMajor": "2",
                "_rallyAPIMinor": "0",
                "_ref": "/slm/webservice/v2.0/subscription/5104",
                "_refObjectUUID": "8edcc979-ce87-48f7-b129-699a393f58d8",
                "_refObjectName": "raytheon_az_-163",
                "_type": "Subscription"
            },
            "Workspace":             {
                "_rallyAPIMajor": "2",
                "_rallyAPIMinor": "0",
                "_ref": "/slm/webservice/v2.0/workspace/69587",
                "_refObjectUUID": "59391212-ec86-42b1-a315-b881f4b94958",
                "_refObjectName": "BSD Workspace",
                "_type": "Workspace"
            },
            "Changesets":             {
                "_rallyAPIMajor": "2",
                "_rallyAPIMinor": "0",
                "_ref": "/slm/webservice/v2.0/HierarchicalRequirement/34295131/Changesets",
                "_type": "Changeset",
                "Count": 0
            },
            "Description": "<ul style=\"margin-top: 0in; margin-bottom: 0in; margin-left: 0.375in; unicode-bidi: embed; direction: ltr;\">  <li style=\"margin-top: 0px; margin-bottom: 0px; vertical-align: middle;\"><span style=\"font-family: Calibri; font-size: 11pt;\">Report - Save as Word      document<\/span><\/li>  <ul style=\"margin-top: 0in; margin-bottom: 0in; margin-left: 0.375in; unicode-bidi: embed; direction: ltr;\">   <li style=\"margin-top: 0px; margin-bottom: 0px; vertical-align: middle;\"><span style=\"font-family: Calibri; font-size: 11pt;\">Enables value copy/paste       into powerpoint instead of screen grab<\/span><\/li>   <li style=\"margin-top: 0px; margin-bottom: 0px; vertical-align: middle;\"><span style=\"font-family: Calibri; font-size: 11pt;\">Another export type<\/span><\/li><\/ul><li style=\"margin-top: 0px; margin-bottom: 0px; vertical-align: middle;\"><span style=\"font-family: Calibri; font-size: 11pt;\"><font face=\"Arial\" size=\"2\">Not available to mobile device users.<\/font><\/span><\/li><ul style=\"margin-top: 0in; margin-bottom: 0in; margin-left: 0.375in; unicode-bidi: embed; direction: ltr;\">  <\/ul> <\/ul>",
            "Discussion":             {
                "_rallyAPIMajor": "2",
                "_rallyAPIMinor": "0",
                "_ref": "/slm/webservice/v2.0/HierarchicalRequirement/34295131/Discussion",
                "_type": "ConversationPost",
                "Count": 0
            },
            "DisplayColor": null,
            "Expedite": false,
            "FormattedID": "US10600",
            "LastUpdateDate": "2016-08-16T22:32:36.103Z",
            "LatestDiscussionAgeInMinutes": null,
            "Milestones":             {
                "_rallyAPIMajor": "2",
                "_rallyAPIMinor": "0",
                "_ref": "/slm/webservice/v2.0/HierarchicalRequirement/34295131/Milestones",
                "_type": "Milestone",
                "_tagsNameArray": [],
                "Count": 0
            },
            "Name": "SubFeature: Report - Create as Word document",
            "Notes": "",
            "Owner":             {
                "_rallyAPIMajor": "2",
                "_rallyAPIMinor": "0",
                "_ref": "/slm/webservice/v2.0/user/33607268",
                "_refObjectUUID": "8b51ad49-d060-41bf-b4d0-918a2466ee43",
                "_refObjectName": "Brad Isbell",
                "_type": "User"
            },
            "Project":             {
                "_rallyAPIMajor": "2",
                "_rallyAPIMinor": "0",
                "_ref": "/slm/webservice/v2.0/project/34279769",
                "_refObjectUUID": "82b32c7c-0e75-4735-a5ba-79099094b552",
                "_refObjectName": "PCD",
                "_type": "Project"
            },
            "Ready": false,
            "RevisionHistory":             {
                "_rallyAPIMajor": "2",
                "_rallyAPIMinor": "0",
                "_ref": "/slm/webservice/v2.0/revisionhistory/34295132",
                "_refObjectUUID": "33a83e48-ec5e-47fa-9b90-dbe076c30cb8",
                "_type": "RevisionHistory"
            },
            "Tags":             {
                "_rallyAPIMajor": "2",
                "_rallyAPIMinor": "0",
                "_ref": "/slm/webservice/v2.0/HierarchicalRequirement/34295131/Tags",
                "_type": "Tag",
                "_tagsNameArray": [],
                "Count": 0
            },
            "LastBuild": null,
            "LastRun": null,
            "PassingTestCaseCount": 0,
            "ScheduleState": "Accepted",
            "TestCaseCount": 0,
            "Attachments":             {
                "_rallyAPIMajor": "2",
                "_rallyAPIMinor": "0",
                "_ref": "/slm/webservice/v2.0/HierarchicalRequirement/34295131/Attachments",
                "_type": "Attachment",
                "Count": 0
            },
            "Package": null,
            "AcceptedDate": "2016-08-16T22:32:36.049Z",
            "Blocked": false,
            "BlockedReason": null,
            "Blocker": null,
            "Children":             {
                "_rallyAPIMajor": "2",
                "_rallyAPIMinor": "0",
                "_ref": "/slm/webservice/v2.0/HierarchicalRequirement/34295131/Children",
                "_type": "HierarchicalRequirement",
                "Count": 0
            },
            "DefectStatus": "NONE",
            "Defects":             {
                "_rallyAPIMajor": "2",
                "_rallyAPIMinor": "0",
                "_ref": "/slm/webservice/v2.0/HierarchicalRequirement/34295131/Defects",
                "_type": "Defect",
                "Count": 0
            },
            "DirectChildrenCount": 0,
            "DragAndDropRank": "P!!VO~~~~~~~~~~~~~~~~~~~~~~~~~~~~~~~~~~~~~~~~~~~~~~~~~~~~~~~~~~~",
            "HasParent": true,
            "InProgressDate": "2016-08-16T22:32:36.049Z",
            "Iteration":             {
                "_rallyAPIMajor": "2",
                "_rallyAPIMinor": "0",
                "_ref": "/slm/webservice/v2.0/iteration/34442967",
                "_refObjectUUID": "08383800-b7e6-442e-a30e-be5266da2952",
                "_refObjectName": "Sprint 09",
                "_type": "Iteration"
            },
            "Parent":             {
                "_rallyAPIMajor": "2",
                "_rallyAPIMinor": "0",
                "_ref": "/slm/webservice/v2.0/hierarchicalrequirement/34294911",
                "_refObjectUUID": "5f75d092-a0e4-4494-802f-7abc1f6d17b8",
                "_refObjectName": "Feature: Generate Report",
                "_type": "HierarchicalRequirement"
            },
            "PlanEstimate": 0,
            "Predecessors":             {
                "_rallyAPIMajor": "2",
                "_rallyAPIMinor": "0",
                "_ref": "/slm/webservice/v2.0/HierarchicalRequirement/34295131/Predecessors",
                "_type": "HierarchicalRequirement",
                "Count": 0
            },
            "Recycled": false,
            "Release":             {
                "_rallyAPIMajor": "2",
                "_rallyAPIMinor": "0",
                "_ref": "/slm/webservice/v2.0/release/34571699",
                "_refObjectUUID": "eacfc27a-ff91-484b-bd7a-45c752f3415d",
                "_refObjectName": "Release 2 Production",
                "_type": "Release"
            },
            "Successors":             {
                "_rallyAPIMajor": "2",
                "_rallyAPIMinor": "0",
                "_ref": "/slm/webservice/v2.0/HierarchicalRequirement/34295131/Successors",
                "_type": "HierarchicalRequirement",
                "Count": 0
            },
            "TaskActualTotal": 0,
            "TaskEstimateTotal": 0,
            "TaskRemainingTotal": 0,
            "TaskStatus": "NONE",
            "Tasks":             {
                "_rallyAPIMajor": "2",
                "_rallyAPIMinor": "0",
                "_ref": "/slm/webservice/v2.0/HierarchicalRequirement/34295131/Tasks",
                "_type": "Task",
                "Count": 0
            },
            "TestCaseStatus": "NONE",
            "TestCases":             {
                "_rallyAPIMajor": "2",
                "_rallyAPIMinor": "0",
                "_ref": "/slm/webservice/v2.0/HierarchicalRequirement/34295131/TestCases",
                "_type": "TestCase",
                "Count": 0
            },
            "c_ACv4ReqID": null,
            "c_AISRequirementID": null,
            "c_ANTReqID": null,
            "c_BizValue": null,
            "c_CAPTSReqID": null,
            "c_COTSAISReqID": null,
            "c_CromaReqID": null,
            "c_EBinderReqID": null,
            "c_EcBinderReqID": null,
            "c_ETSCReqID": null,
            "Feature": null,
            "c_FRACASReqID": null,
            "c_HRRAReqID": null,
            "c_ITRRReqID": null,
            "c_MsfReqID": null,
            "c_NBIDCReqID": null,
            "c_NFDEReqID": null,
            "c_PARTSReqID": null,
            "c_PMRTReqID": null,
            "c_POAcceptanceCriteria": null,
            "PortfolioItem": null,
            "c_QCAttachments": null,
            "c_QCReqID": null,
            "c_QES2ReqID": null,
            "c_QES2ReqIDDELETED": null,
            "c_Qt2ReqID": null,
            "c_QT3ReqID": null,
            "c_RaMPReqID": null,
            "c_RfutureReqID": null,
            "c_RgemsReqID": null,
            "c_RISCATSReqID": null,
            "c_RLabsReqID": null,
            "c_SABSSReqID": null,
            "c_SabssReqIddelete": null,
            "c_SOCRReqID": null,
            "c_SRDReqID": null,
            "c_SUPSRSRqmtID": null,
            "c_SysReqID": null,
            "c_TandCReqIDCOTS": null,
            "c_TermsandConditionsReqID": null,
            "c_TripodReqID": null,
            "_type": "HierarchicalRequirement"
        },
                {
            "_rallyAPIMajor": "2",
            "_rallyAPIMinor": "0",
            "_ref": "/slm/webservice/v2.0/hierarchicalrequirement/34295184",
            "_refObjectUUID": "aa16abc7-39d9-40b4-a4f2-b528199b31da",
            "_objectVersion": "28",
            "_refObjectName": "As a user, I can save my report to a dynamically created RShare location that will be viewed in the ITP app",
            "CreationDate": "2016-03-09T16:23:19.914Z",
            "_CreatedAt": "Mar 9, 2016",
            "ObjectID": 34295184,
            "VersionId": "28",
            "Subscription":             {
                "_rallyAPIMajor": "2",
                "_rallyAPIMinor": "0",
                "_ref": "/slm/webservice/v2.0/subscription/5104",
                "_refObjectUUID": "8edcc979-ce87-48f7-b129-699a393f58d8",
                "_refObjectName": "raytheon_az_-163",
                "_type": "Subscription"
            },
            "Workspace":             {
                "_rallyAPIMajor": "2",
                "_rallyAPIMinor": "0",
                "_ref": "/slm/webservice/v2.0/workspace/69587",
                "_refObjectUUID": "59391212-ec86-42b1-a315-b881f4b94958",
                "_refObjectName": "BSD Workspace",
                "_type": "Workspace"
            },
            "Changesets":             {
                "_rallyAPIMajor": "2",
                "_rallyAPIMinor": "0",
                "_ref": "/slm/webservice/v2.0/HierarchicalRequirement/34295184/Changesets",
                "_type": "Changeset",
                "Count": 0
            },
            "Description": "<ul class=\"rally-rte-class-0d33f28939247\">  <\/ul><p class=\"rally-rte-class-0b0d35fe2c436e8\"><span class=\"rally-rte-class-0ba29cdaec7fc6\">Requirements notes:<\/span><span class=\"rally-rte-class-0ba29cdaec7fc6\"><br /><\/span><\/p><p class=\"rally-rte-class-0b0d35fe2c436e8\"><span class=\"rally-rte-class-0ba29cdaec7fc6\">User clicks \"Send to ITP\"<\/span><\/p><p class=\"rally-rte-class-0b0d35fe2c436e8\"><span class=\"rally-rte-class-0ba29cdaec7fc6\">PCD web app checks to see if logged User has an ITP Rshare directory under the \"PCD Reports\" folder.<\/span><\/p><p class=\"rally-rte-class-0b0d35fe2c436e8\"><span class=\"rally-rte-class-0ba29cdaec7fc6\">If they do have an ITP directory, then write the file.<\/span><\/p><p class=\"rally-rte-class-0b0d35fe2c436e8\"><span class=\"rally-rte-class-0ba29cdaec7fc6\">******<span class=\"rally-rte-class-0ba29cdaec7fc6\">******<span class=\"rally-rte-class-0ba29cdaec7fc6\">******<span class=\"rally-rte-class-0ba29cdaec7fc6\">******<span class=\"rally-rte-class-0ba29cdaec7fc6\">******<span class=\"rally-rte-class-0ba29cdaec7fc6\">******<span class=\"rally-rte-class-0ba29cdaec7fc6\">******<span class=\"rally-rte-class-0ba29cdaec7fc6\">******<span class=\"rally-rte-class-0ba29cdaec7fc6\">******<span class=\"rally-rte-class-0ba29cdaec7fc6\">******<span class=\"rally-rte-class-0ba29cdaec7fc6\">******<span class=\"rally-rte-class-0ba29cdaec7fc6\">******<span class=\"rally-rte-class-0ba29cdaec7fc6\">******<span class=\"rally-rte-class-0ba29cdaec7fc6\">******<span class=\"rally-rte-class-0ba29cdaec7fc6\">******<span class=\"rally-rte-class-0ba29cdaec7fc6\">******<span class=\"rally-rte-class-0ba29cdaec7fc6\">******<span class=\"rally-rte-class-0ba29cdaec7fc6\">******<\/span><\/span><\/span><\/span><\/span><\/span><\/span><\/span><\/span><\/span><\/span><\/span><\/span><\/span><\/span><\/span><\/span><br />NOT FEASIBLE. ALL PCD USERS WOULD NEED TO BE ADMINS IN ITP TO ACHIEVE THIS<br /><span class=\"rally-rte-class-0ba29cdaec7fc6\">******<span class=\"rally-rte-class-0ba29cdaec7fc6\">******<span class=\"rally-rte-class-0ba29cdaec7fc6\">******<span class=\"rally-rte-class-0ba29cdaec7fc6\">******<span class=\"rally-rte-class-0ba29cdaec7fc6\">******<span class=\"rally-rte-class-0ba29cdaec7fc6\">******<span class=\"rally-rte-class-0ba29cdaec7fc6\">******<span class=\"rally-rte-class-0ba29cdaec7fc6\">******<span class=\"rally-rte-class-0ba29cdaec7fc6\">******<span class=\"rally-rte-class-0ba29cdaec7fc6\">******<span class=\"rally-rte-class-0ba29cdaec7fc6\">******<span class=\"rally-rte-class-0ba29cdaec7fc6\">******<span class=\"rally-rte-class-0ba29cdaec7fc6\">******<span class=\"rally-rte-class-0ba29cdaec7fc6\">******<span class=\"rally-rte-class-0ba29cdaec7fc6\">******<span class=\"rally-rte-class-0ba29cdaec7fc6\">******<span class=\"rally-rte-class-0ba29cdaec7fc6\">******<span class=\"rally-rte-class-0ba29cdaec7fc6\">******<\/span><\/span><\/span><\/span><\/span><\/span><\/span><\/span><\/span><\/span><\/span><\/span><\/span><\/span><\/span><\/span><\/span><\/span><br />If they don't have an ITP directory (see attached screenshot):<br />Create a folder for the user with the foldername = Peoplesoft IT.<br />Give the RShare \"PCD Reports Admins\" user group \"Contribute\" permissions the new folder.<br />Give the RShare \"RMS LT Administrators\" user group \"Full Control\" permissions to the new folder.<br />Give the logged in user \"Contribute\" permission on this folder.<br />Then write the file to the new folder.<br /><span class=\"rally-rte-class-0ba29cdaec7fc6\">******<span class=\"rally-rte-class-0ba29cdaec7fc6\">******<span class=\"rally-rte-class-0ba29cdaec7fc6\">******<span class=\"rally-rte-class-0ba29cdaec7fc6\">******<span class=\"rally-rte-class-0ba29cdaec7fc6\">******<span class=\"rally-rte-class-0ba29cdaec7fc6\">******<span class=\"rally-rte-class-0ba29cdaec7fc6\">******<span class=\"rally-rte-class-0ba29cdaec7fc6\">******<span class=\"rally-rte-class-0ba29cdaec7fc6\">******<span class=\"rally-rte-class-0ba29cdaec7fc6\">******<span class=\"rally-rte-class-0ba29cdaec7fc6\">******<span class=\"rally-rte-class-0ba29cdaec7fc6\">******<span class=\"rally-rte-class-0ba29cdaec7fc6\">******<span class=\"rally-rte-class-0ba29cdaec7fc6\">******<span class=\"rally-rte-class-0ba29cdaec7fc6\">******<span class=\"rally-rte-class-0ba29cdaec7fc6\">******<span class=\"rally-rte-class-0ba29cdaec7fc6\">******<span class=\"rally-rte-class-0ba29cdaec7fc6\">******<\/span><\/span><\/span><\/span><\/span><\/span><\/span><\/span><\/span><\/span><\/span><\/span><\/span><\/span><\/span><\/span><\/span><\/span><\/span><\/p><p class=\"rally-rte-class-0b0d35fe2c436e8\"><span class=\"rally-rte-class-0ba29cdaec7fc6\">The app itself, the may need ITP Approved Users role.<\/span><\/p><p class=\"rally-rte-class-0b0d35fe2c436e8\"><span class=\"rally-rte-class-0ba29cdaec7fc6\"><br /><\/span><\/p><ul class=\"rally-rte-class-0d33f28939247\"><ul class=\"rally-rte-class-0b6896c6857992\">  <\/ul> <\/ul>",
            "Discussion":             {
                "_rallyAPIMajor": "2",
                "_rallyAPIMinor": "0",
                "_ref": "/slm/webservice/v2.0/HierarchicalRequirement/34295184/Discussion",
                "_type": "ConversationPost",
                "Count": 0
            },
            "DisplayColor": null,
            "Expedite": false,
            "FormattedID": "US10601",
            "LastUpdateDate": "2016-09-19T21:28:09.218Z",
            "LatestDiscussionAgeInMinutes": null,
            "Milestones":             {
                "_rallyAPIMajor": "2",
                "_rallyAPIMinor": "0",
                "_ref": "/slm/webservice/v2.0/HierarchicalRequirement/34295184/Milestones",
                "_type": "Milestone",
                "_tagsNameArray": [],
                "Count": 0
            },
            "Name": "As a user, I can save my report to a dynamically created RShare location that will be viewed in the ITP app",
            "Notes": "",
            "Owner":             {
                "_rallyAPIMajor": "2",
                "_rallyAPIMinor": "0",
                "_ref": "/slm/webservice/v2.0/user/33607268",
                "_refObjectUUID": "8b51ad49-d060-41bf-b4d0-918a2466ee43",
                "_refObjectName": "Brad Isbell",
                "_type": "User"
            },
            "Project":             {
                "_rallyAPIMajor": "2",
                "_rallyAPIMinor": "0",
                "_ref": "/slm/webservice/v2.0/project/34279769",
                "_refObjectUUID": "82b32c7c-0e75-4735-a5ba-79099094b552",
                "_refObjectName": "PCD",
                "_type": "Project"
            },
            "Ready": false,
            "RevisionHistory":             {
                "_rallyAPIMajor": "2",
                "_rallyAPIMinor": "0",
                "_ref": "/slm/webservice/v2.0/revisionhistory/34295185",
                "_refObjectUUID": "681392bf-b8b1-45d3-a654-4b099f2209bc",
                "_type": "RevisionHistory"
            },
            "Tags":             {
                "_rallyAPIMajor": "2",
                "_rallyAPIMinor": "0",
                "_ref": "/slm/webservice/v2.0/HierarchicalRequirement/34295184/Tags",
                "_type": "Tag",
                "_tagsNameArray": [],
                "Count": 0
            },
            "LastBuild": null,
            "LastRun": null,
            "PassingTestCaseCount": 0,
            "ScheduleState": "Defined",
            "TestCaseCount": 0,
            "Attachments":             {
                "_rallyAPIMajor": "2",
                "_rallyAPIMinor": "0",
                "_ref": "/slm/webservice/v2.0/HierarchicalRequirement/34295184/Attachments",
                "_type": "Attachment",
                "Count": 1
            },
            "Package": null,
            "AcceptedDate": null,
            "Blocked": false,
            "BlockedReason": null,
            "Blocker": null,
            "Children":             {
                "_rallyAPIMajor": "2",
                "_rallyAPIMinor": "0",
                "_ref": "/slm/webservice/v2.0/HierarchicalRequirement/34295184/Children",
                "_type": "HierarchicalRequirement",
                "Count": 0
            },
            "DefectStatus": "NONE",
            "Defects":             {
                "_rallyAPIMajor": "2",
                "_rallyAPIMinor": "0",
                "_ref": "/slm/webservice/v2.0/HierarchicalRequirement/34295184/Defects",
                "_type": "Defect",
                "Count": 0
            },
            "DirectChildrenCount": 0,
            "DragAndDropRank": "P!!VORy,gO~~~~~~~~~~~~~~~~~~~~~~~~~~~~~~~~~~~~~~~~~~~~~~~~~~~~~~",
            "HasParent": true,
            "InProgressDate": null,
            "Iteration": null,
            "Parent":             {
                "_rallyAPIMajor": "2",
                "_rallyAPIMinor": "0",
                "_ref": "/slm/webservice/v2.0/hierarchicalrequirement/34294911",
                "_refObjectUUID": "5f75d092-a0e4-4494-802f-7abc1f6d17b8",
                "_refObjectName": "Feature: Generate Report",
                "_type": "HierarchicalRequirement"
            },
            "PlanEstimate": 13,
            "Predecessors":             {
                "_rallyAPIMajor": "2",
                "_rallyAPIMinor": "0",
                "_ref": "/slm/webservice/v2.0/HierarchicalRequirement/34295184/Predecessors",
                "_type": "HierarchicalRequirement",
                "Count": 0
            },
            "Recycled": false,
            "Release": null,
            "Successors":             {
                "_rallyAPIMajor": "2",
                "_rallyAPIMinor": "0",
                "_ref": "/slm/webservice/v2.0/HierarchicalRequirement/34295184/Successors",
                "_type": "HierarchicalRequirement",
                "Count": 0
            },
            "TaskActualTotal": 0,
            "TaskEstimateTotal": 0,
            "TaskRemainingTotal": 0,
            "TaskStatus": "NONE",
            "Tasks":             {
                "_rallyAPIMajor": "2",
                "_rallyAPIMinor": "0",
                "_ref": "/slm/webservice/v2.0/HierarchicalRequirement/34295184/Tasks",
                "_type": "Task",
                "Count": 0
            },
            "TestCaseStatus": "NONE",
            "TestCases":             {
                "_rallyAPIMajor": "2",
                "_rallyAPIMinor": "0",
                "_ref": "/slm/webservice/v2.0/HierarchicalRequirement/34295184/TestCases",
                "_type": "TestCase",
                "Count": 0
            },
            "c_ACv4ReqID": null,
            "c_AISRequirementID": null,
            "c_ANTReqID": null,
            "c_BizValue": null,
            "c_CAPTSReqID": null,
            "c_COTSAISReqID": null,
            "c_CromaReqID": null,
            "c_EBinderReqID": null,
            "c_EcBinderReqID": null,
            "c_ETSCReqID": null,
            "Feature": null,
            "c_FRACASReqID": null,
            "c_HRRAReqID": null,
            "c_ITRRReqID": null,
            "c_MsfReqID": null,
            "c_NBIDCReqID": null,
            "c_NFDEReqID": null,
            "c_PARTSReqID": null,
            "c_PMRTReqID": null,
            "c_POAcceptanceCriteria": null,
            "PortfolioItem": null,
            "c_QCAttachments": null,
            "c_QCReqID": null,
            "c_QES2ReqID": null,
            "c_QES2ReqIDDELETED": null,
            "c_Qt2ReqID": null,
            "c_QT3ReqID": null,
            "c_RaMPReqID": null,
            "c_RfutureReqID": null,
            "c_RgemsReqID": null,
            "c_RISCATSReqID": null,
            "c_RLabsReqID": null,
            "c_SABSSReqID": null,
            "c_SabssReqIddelete": null,
            "c_SOCRReqID": null,
            "c_SRDReqID": null,
            "c_SUPSRSRqmtID": null,
            "c_SysReqID": null,
            "c_TandCReqIDCOTS": null,
            "c_TermsandConditionsReqID": null,
            "c_TripodReqID": null,
            "_type": "HierarchicalRequirement"
        },
                {
            "_rallyAPIMajor": "2",
            "_rallyAPIMinor": "0",
            "_ref": "/slm/webservice/v2.0/hierarchicalrequirement/34316237",
            "_refObjectUUID": "e32d848a-c390-4e38-a749-3c116e5b7092",
            "_objectVersion": "37",
            "_refObjectName": "As a user, I can select layout report options so that I can define report generation.",
            "CreationDate": "2016-03-11T20:16:45.729Z",
            "_CreatedAt": "Mar 11, 2016",
            "ObjectID": 34316237,
            "VersionId": "37",
            "Subscription":             {
                "_rallyAPIMajor": "2",
                "_rallyAPIMinor": "0",
                "_ref": "/slm/webservice/v2.0/subscription/5104",
                "_refObjectUUID": "8edcc979-ce87-48f7-b129-699a393f58d8",
                "_refObjectName": "raytheon_az_-163",
                "_type": "Subscription"
            },
            "Workspace":             {
                "_rallyAPIMajor": "2",
                "_rallyAPIMinor": "0",
                "_ref": "/slm/webservice/v2.0/workspace/69587",
                "_refObjectUUID": "59391212-ec86-42b1-a315-b881f4b94958",
                "_refObjectName": "BSD Workspace",
                "_type": "Workspace"
            },
            "Changesets":             {
                "_rallyAPIMajor": "2",
                "_rallyAPIMinor": "0",
                "_ref": "/slm/webservice/v2.0/HierarchicalRequirement/34316237/Changesets",
                "_type": "Changeset",
                "Count": 0
            },
            "Description": "<p>Please see QC req=95 and req=100.<br /><\/p>",
            "Discussion":             {
                "_rallyAPIMajor": "2",
                "_rallyAPIMinor": "0",
                "_ref": "/slm/webservice/v2.0/HierarchicalRequirement/34316237/Discussion",
                "_type": "ConversationPost",
                "Count": 0
            },
            "DisplayColor": null,
            "Expedite": false,
            "FormattedID": "US10644",
            "LastUpdateDate": "2016-06-23T18:45:19.749Z",
            "LatestDiscussionAgeInMinutes": null,
            "Milestones":             {
                "_rallyAPIMajor": "2",
                "_rallyAPIMinor": "0",
                "_ref": "/slm/webservice/v2.0/HierarchicalRequirement/34316237/Milestones",
                "_type": "Milestone",
                "_tagsNameArray": [],
                "Count": 0
            },
            "Name": "As a user, I can select layout report options so that I can define report generation.",
            "Notes": "",
            "Owner":             {
                "_rallyAPIMajor": "2",
                "_rallyAPIMinor": "0",
                "_ref": "/slm/webservice/v2.0/user/33607268",
                "_refObjectUUID": "8b51ad49-d060-41bf-b4d0-918a2466ee43",
                "_refObjectName": "Brad Isbell",
                "_type": "User"
            },
            "Project":             {
                "_rallyAPIMajor": "2",
                "_rallyAPIMinor": "0",
                "_ref": "/slm/webservice/v2.0/project/34279769",
                "_refObjectUUID": "82b32c7c-0e75-4735-a5ba-79099094b552",
                "_refObjectName": "PCD",
                "_type": "Project"
            },
            "Ready": false,
            "RevisionHistory":             {
                "_rallyAPIMajor": "2",
                "_rallyAPIMinor": "0",
                "_ref": "/slm/webservice/v2.0/revisionhistory/34316238",
                "_refObjectUUID": "886a8670-a31b-4a75-8893-798a9121863a",
                "_type": "RevisionHistory"
            },
            "Tags":             {
                "_rallyAPIMajor": "2",
                "_rallyAPIMinor": "0",
                "_ref": "/slm/webservice/v2.0/HierarchicalRequirement/34316237/Tags",
                "_type": "Tag",
                "_tagsNameArray": [],
                "Count": 0
            },
            "LastBuild": null,
            "LastRun": null,
            "PassingTestCaseCount": 0,
            "ScheduleState": "Accepted",
            "TestCaseCount": 0,
            "Attachments":             {
                "_rallyAPIMajor": "2",
                "_rallyAPIMinor": "0",
                "_ref": "/slm/webservice/v2.0/HierarchicalRequirement/34316237/Attachments",
                "_type": "Attachment",
                "Count": 0
            },
            "Package": null,
            "AcceptedDate": "2016-06-23T18:45:19.673Z",
            "Blocked": false,
            "BlockedReason": null,
            "Blocker": null,
            "Children":             {
                "_rallyAPIMajor": "2",
                "_rallyAPIMinor": "0",
                "_ref": "/slm/webservice/v2.0/HierarchicalRequirement/34316237/Children",
                "_type": "HierarchicalRequirement",
                "Count": 0
            },
            "DefectStatus": "NONE",
            "Defects":             {
                "_rallyAPIMajor": "2",
                "_rallyAPIMinor": "0",
                "_ref": "/slm/webservice/v2.0/HierarchicalRequirement/34316237/Defects",
                "_type": "Defect",
                "Count": 0
            },
            "DirectChildrenCount": 0,
            "DragAndDropRank": ",~~kSs8P#@8yCKZ!%O;%KP297#y,gP!!!!!!!!!!!!!!!!!!!!!!!!!!!!!!!!!!",
            "HasParent": true,
            "InProgressDate": "2016-05-09T18:26:38.544Z",
            "Iteration":             {
                "_rallyAPIMajor": "2",
                "_rallyAPIMinor": "0",
                "_ref": "/slm/webservice/v2.0/iteration/34442829",
                "_refObjectUUID": "412c800b-a6b0-444b-b977-bd46a396a75b",
                "_refObjectName": "Sprint 03",
                "_type": "Iteration"
            },
            "Parent":             {
                "_rallyAPIMajor": "2",
                "_rallyAPIMinor": "0",
                "_ref": "/slm/webservice/v2.0/hierarchicalrequirement/34294911",
                "_refObjectUUID": "5f75d092-a0e4-4494-802f-7abc1f6d17b8",
                "_refObjectName": "Feature: Generate Report",
                "_type": "HierarchicalRequirement"
            },
            "PlanEstimate": 15,
            "Predecessors":             {
                "_rallyAPIMajor": "2",
                "_rallyAPIMinor": "0",
                "_ref": "/slm/webservice/v2.0/HierarchicalRequirement/34316237/Predecessors",
                "_type": "HierarchicalRequirement",
                "Count": 0
            },
            "Recycled": false,
            "Release":             {
                "_rallyAPIMajor": "2",
                "_rallyAPIMinor": "0",
                "_ref": "/slm/webservice/v2.0/release/34424667",
                "_refObjectUUID": "42ed78aa-a3c3-43b9-95c8-7238de2fff77",
                "_refObjectName": "Release 1 Farnborough",
                "_type": "Release"
            },
            "Successors":             {
                "_rallyAPIMajor": "2",
                "_rallyAPIMinor": "0",
                "_ref": "/slm/webservice/v2.0/HierarchicalRequirement/34316237/Successors",
                "_type": "HierarchicalRequirement",
                "Count": 0
            },
            "TaskActualTotal": 11,
            "TaskEstimateTotal": 19,
            "TaskRemainingTotal": 0,
            "TaskStatus": "COMPLETED",
            "Tasks":             {
                "_rallyAPIMajor": "2",
                "_rallyAPIMinor": "0",
                "_ref": "/slm/webservice/v2.0/HierarchicalRequirement/34316237/Tasks",
                "_type": "Task",
                "Count": 5
            },
            "TestCaseStatus": "NONE",
            "TestCases":             {
                "_rallyAPIMajor": "2",
                "_rallyAPIMinor": "0",
                "_ref": "/slm/webservice/v2.0/HierarchicalRequirement/34316237/TestCases",
                "_type": "TestCase",
                "Count": 0
            },
            "c_ACv4ReqID": null,
            "c_AISRequirementID": null,
            "c_ANTReqID": null,
            "c_BizValue": null,
            "c_CAPTSReqID": null,
            "c_COTSAISReqID": null,
            "c_CromaReqID": null,
            "c_EBinderReqID": null,
            "c_EcBinderReqID": null,
            "c_ETSCReqID": null,
            "Feature": null,
            "c_FRACASReqID": null,
            "c_HRRAReqID": null,
            "c_ITRRReqID": null,
            "c_MsfReqID": null,
            "c_NBIDCReqID": null,
            "c_NFDEReqID": null,
            "c_PARTSReqID": null,
            "c_PMRTReqID": null,
            "c_POAcceptanceCriteria": null,
            "PortfolioItem": null,
            "c_QCAttachments": null,
            "c_QCReqID": null,
            "c_QES2ReqID": null,
            "c_QES2ReqIDDELETED": null,
            "c_Qt2ReqID": null,
            "c_QT3ReqID": null,
            "c_RaMPReqID": null,
            "c_RfutureReqID": null,
            "c_RgemsReqID": null,
            "c_RISCATSReqID": null,
            "c_RLabsReqID": null,
            "c_SABSSReqID": null,
            "c_SabssReqIddelete": null,
            "c_SOCRReqID": null,
            "c_SRDReqID": null,
            "c_SUPSRSRqmtID": null,
            "c_SysReqID": null,
            "c_TandCReqIDCOTS": null,
            "c_TermsandConditionsReqID": null,
            "c_TripodReqID": null,
            "_type": "HierarchicalRequirement"
        },
                {
            "_rallyAPIMajor": "2",
            "_rallyAPIMinor": "0",
            "_ref": "/slm/webservice/v2.0/hierarchicalrequirement/34769457",
            "_refObjectUUID": "e99e8e03-45b3-40c2-853c-c3cd29d77ad7",
            "_objectVersion": "42",
            "_refObjectName": "As a user, I can email the report to myself using a RefApp 5 microservice",
            "CreationDate": "2016-06-06T17:55:38.479Z",
            "_CreatedAt": "Jun 6, 2016",
            "ObjectID": 34769457,
            "VersionId": "42",
            "Subscription":             {
                "_rallyAPIMajor": "2",
                "_rallyAPIMinor": "0",
                "_ref": "/slm/webservice/v2.0/subscription/5104",
                "_refObjectUUID": "8edcc979-ce87-48f7-b129-699a393f58d8",
                "_refObjectName": "raytheon_az_-163",
                "_type": "Subscription"
            },
            "Workspace":             {
                "_rallyAPIMajor": "2",
                "_rallyAPIMinor": "0",
                "_ref": "/slm/webservice/v2.0/workspace/69587",
                "_refObjectUUID": "59391212-ec86-42b1-a315-b881f4b94958",
                "_refObjectName": "BSD Workspace",
                "_type": "Workspace"
            },
            "Changesets":             {
                "_rallyAPIMajor": "2",
                "_rallyAPIMinor": "0",
                "_ref": "/slm/webservice/v2.0/HierarchicalRequirement/34769457/Changesets",
                "_type": "Changeset",
                "Count": 0
            },
            "Description": "<p>Once the user has previewed the document, one of their saving options is to have the report emailed to themselves. They will click the Email button on the report options page, the email will be sent, and a confirmation message will be presented informing them that the email had been sent and to which address it was sent to.<\/p>",
            "Discussion":             {
                "_rallyAPIMajor": "2",
                "_rallyAPIMinor": "0",
                "_ref": "/slm/webservice/v2.0/HierarchicalRequirement/34769457/Discussion",
                "_type": "ConversationPost",
                "Count": 0
            },
            "DisplayColor": null,
            "Expedite": false,
            "FormattedID": "US10900",
            "LastUpdateDate": "2016-09-19T21:10:55.164Z",
            "LatestDiscussionAgeInMinutes": null,
            "Milestones":             {
                "_rallyAPIMajor": "2",
                "_rallyAPIMinor": "0",
                "_ref": "/slm/webservice/v2.0/HierarchicalRequirement/34769457/Milestones",
                "_type": "Milestone",
                "_tagsNameArray": [],
                "Count": 0
            },
            "Name": "As a user, I can email the report to myself using a RefApp 5 microservice",
            "Notes": "",
            "Owner":             {
                "_rallyAPIMajor": "2",
                "_rallyAPIMinor": "0",
                "_ref": "/slm/webservice/v2.0/user/33607268",
                "_refObjectUUID": "8b51ad49-d060-41bf-b4d0-918a2466ee43",
                "_refObjectName": "Brad Isbell",
                "_type": "User"
            },
            "Project":             {
                "_rallyAPIMajor": "2",
                "_rallyAPIMinor": "0",
                "_ref": "/slm/webservice/v2.0/project/34279769",
                "_refObjectUUID": "82b32c7c-0e75-4735-a5ba-79099094b552",
                "_refObjectName": "PCD",
                "_type": "Project"
            },
            "Ready": false,
            "RevisionHistory":             {
                "_rallyAPIMajor": "2",
                "_rallyAPIMinor": "0",
                "_ref": "/slm/webservice/v2.0/revisionhistory/34769458",
                "_refObjectUUID": "1a4d4242-fd70-4842-bf31-a93c079ed891",
                "_type": "RevisionHistory"
            },
            "Tags":             {
                "_rallyAPIMajor": "2",
                "_rallyAPIMinor": "0",
                "_ref": "/slm/webservice/v2.0/HierarchicalRequirement/34769457/Tags",
                "_type": "Tag",
                "_tagsNameArray": [],
                "Count": 0
            },
            "LastBuild": null,
            "LastRun": null,
            "PassingTestCaseCount": 0,
            "ScheduleState": "In-Progress",
            "TestCaseCount": 0,
            "Attachments":             {
                "_rallyAPIMajor": "2",
                "_rallyAPIMinor": "0",
                "_ref": "/slm/webservice/v2.0/HierarchicalRequirement/34769457/Attachments",
                "_type": "Attachment",
                "Count": 0
            },
            "Package": null,
            "AcceptedDate": null,
            "Blocked": false,
            "BlockedReason": null,
            "Blocker": null,
            "Children":             {
                "_rallyAPIMajor": "2",
                "_rallyAPIMinor": "0",
                "_ref": "/slm/webservice/v2.0/HierarchicalRequirement/34769457/Children",
                "_type": "HierarchicalRequirement",
                "Count": 0
            },
            "DefectStatus": "NONE",
            "Defects":             {
                "_rallyAPIMajor": "2",
                "_rallyAPIMinor": "0",
                "_ref": "/slm/webservice/v2.0/HierarchicalRequirement/34769457/Defects",
                "_type": "Defect",
                "Count": 0
            },
            "DirectChildrenCount": 0,
            "DragAndDropRank": "P!!VOO~~~~~~~~~~~~~~~~~~~~~~~~~~~~~~~~~~~~~~~~~~~~~~~~~~~~~~~~~~",
            "HasParent": true,
            "InProgressDate": "2016-06-07T02:31:01.098Z",
            "Iteration": null,
            "Parent":             {
                "_rallyAPIMajor": "2",
                "_rallyAPIMinor": "0",
                "_ref": "/slm/webservice/v2.0/hierarchicalrequirement/34294911",
                "_refObjectUUID": "5f75d092-a0e4-4494-802f-7abc1f6d17b8",
                "_refObjectName": "Feature: Generate Report",
                "_type": "HierarchicalRequirement"
            },
            "PlanEstimate": 13,
            "Predecessors":             {
                "_rallyAPIMajor": "2",
                "_rallyAPIMinor": "0",
                "_ref": "/slm/webservice/v2.0/HierarchicalRequirement/34769457/Predecessors",
                "_type": "HierarchicalRequirement",
                "Count": 0
            },
            "Recycled": false,
            "Release": null,
            "Successors":             {
                "_rallyAPIMajor": "2",
                "_rallyAPIMinor": "0",
                "_ref": "/slm/webservice/v2.0/HierarchicalRequirement/34769457/Successors",
                "_type": "HierarchicalRequirement",
                "Count": 0
            },
            "TaskActualTotal": 10.75,
            "TaskEstimateTotal": 51.5,
            "TaskRemainingTotal": 40.75,
            "TaskStatus": "IN_PROGRESS",
            "Tasks":             {
                "_rallyAPIMajor": "2",
                "_rallyAPIMinor": "0",
                "_ref": "/slm/webservice/v2.0/HierarchicalRequirement/34769457/Tasks",
                "_type": "Task",
                "Count": 11
            },
            "TestCaseStatus": "NONE",
            "TestCases":             {
                "_rallyAPIMajor": "2",
                "_rallyAPIMinor": "0",
                "_ref": "/slm/webservice/v2.0/HierarchicalRequirement/34769457/TestCases",
                "_type": "TestCase",
                "Count": 0
            },
            "c_ACv4ReqID": null,
            "c_AISRequirementID": null,
            "c_ANTReqID": null,
            "c_BizValue": null,
            "c_CAPTSReqID": null,
            "c_COTSAISReqID": null,
            "c_CromaReqID": null,
            "c_EBinderReqID": null,
            "c_EcBinderReqID": null,
            "c_ETSCReqID": null,
            "Feature": null,
            "c_FRACASReqID": null,
            "c_HRRAReqID": null,
            "c_ITRRReqID": null,
            "c_MsfReqID": null,
            "c_NBIDCReqID": null,
            "c_NFDEReqID": null,
            "c_PARTSReqID": null,
            "c_PMRTReqID": null,
            "c_POAcceptanceCriteria": null,
            "PortfolioItem": null,
            "c_QCAttachments": null,
            "c_QCReqID": null,
            "c_QES2ReqID": null,
            "c_QES2ReqIDDELETED": null,
            "c_Qt2ReqID": null,
            "c_QT3ReqID": null,
            "c_RaMPReqID": null,
            "c_RfutureReqID": null,
            "c_RgemsReqID": null,
            "c_RISCATSReqID": null,
            "c_RLabsReqID": null,
            "c_SABSSReqID": null,
            "c_SabssReqIddelete": null,
            "c_SOCRReqID": null,
            "c_SRDReqID": null,
            "c_SUPSRSRqmtID": null,
            "c_SysReqID": null,
            "c_TandCReqIDCOTS": null,
            "c_TermsandConditionsReqID": null,
            "c_TripodReqID": null,
            "_type": "HierarchicalRequirement"
        },
                {
            "_rallyAPIMajor": "2",
            "_rallyAPIMinor": "0",
            "_ref": "/slm/webservice/v2.0/hierarchicalrequirement/34806108",
            "_refObjectUUID": "38a7866a-7b44-482e-80b0-3ed8a50af117",
            "_objectVersion": "20",
            "_refObjectName": "As an coordinator (new system role), I need to send reports to other people's ITP folder in addition to my own so I can prepare execs ITP folders.",
            "CreationDate": "2016-06-17T21:45:17.551Z",
            "_CreatedAt": "Jun 17, 2016",
            "ObjectID": 34806108,
            "VersionId": "20",
            "Subscription":             {
                "_rallyAPIMajor": "2",
                "_rallyAPIMinor": "0",
                "_ref": "/slm/webservice/v2.0/subscription/5104",
                "_refObjectUUID": "8edcc979-ce87-48f7-b129-699a393f58d8",
                "_refObjectName": "raytheon_az_-163",
                "_type": "Subscription"
            },
            "Workspace":             {
                "_rallyAPIMajor": "2",
                "_rallyAPIMinor": "0",
                "_ref": "/slm/webservice/v2.0/workspace/69587",
                "_refObjectUUID": "59391212-ec86-42b1-a315-b881f4b94958",
                "_refObjectName": "BSD Workspace",
                "_type": "Workspace"
            },
            "Changesets":             {
                "_rallyAPIMajor": "2",
                "_rallyAPIMinor": "0",
                "_ref": "/slm/webservice/v2.0/HierarchicalRequirement/34806108/Changesets",
                "_type": "Changeset",
                "Count": 0
            },
            "Description": "This assumes that proper Rshare permissions have already been granted to the coordinator allowing her/him to write the file.",
            "Discussion":             {
                "_rallyAPIMajor": "2",
                "_rallyAPIMinor": "0",
                "_ref": "/slm/webservice/v2.0/HierarchicalRequirement/34806108/Discussion",
                "_type": "ConversationPost",
                "Count": 0
            },
            "DisplayColor": null,
            "Expedite": false,
            "FormattedID": "US10904",
            "LastUpdateDate": "2016-10-18T23:04:32.281Z",
            "LatestDiscussionAgeInMinutes": null,
            "Milestones":             {
                "_rallyAPIMajor": "2",
                "_rallyAPIMinor": "0",
                "_ref": "/slm/webservice/v2.0/HierarchicalRequirement/34806108/Milestones",
                "_type": "Milestone",
                "_tagsNameArray": [],
                "Count": 0
            },
            "Name": "As an coordinator (new system role), I need to send reports to other people's ITP folder in addition to my own so I can prepare execs ITP folders.",
            "Notes": "",
            "Owner":             {
                "_rallyAPIMajor": "2",
                "_rallyAPIMinor": "0",
                "_ref": "/slm/webservice/v2.0/user/33607268",
                "_refObjectUUID": "8b51ad49-d060-41bf-b4d0-918a2466ee43",
                "_refObjectName": "Brad Isbell",
                "_type": "User"
            },
            "Project":             {
                "_rallyAPIMajor": "2",
                "_rallyAPIMinor": "0",
                "_ref": "/slm/webservice/v2.0/project/34279769",
                "_refObjectUUID": "82b32c7c-0e75-4735-a5ba-79099094b552",
                "_refObjectName": "PCD",
                "_type": "Project"
            },
            "Ready": false,
            "RevisionHistory":             {
                "_rallyAPIMajor": "2",
                "_rallyAPIMinor": "0",
                "_ref": "/slm/webservice/v2.0/revisionhistory/34806109",
                "_refObjectUUID": "7134689b-d716-4f75-93e6-46852cb0d107",
                "_type": "RevisionHistory"
            },
            "Tags":             {
                "_rallyAPIMajor": "2",
                "_rallyAPIMinor": "0",
                "_ref": "/slm/webservice/v2.0/HierarchicalRequirement/34806108/Tags",
                "_type": "Tag",
                "_tagsNameArray": [],
                "Count": 0
            },
            "LastBuild": null,
            "LastRun": null,
            "PassingTestCaseCount": 0,
            "ScheduleState": "Accepted",
            "TestCaseCount": 0,
            "Attachments":             {
                "_rallyAPIMajor": "2",
                "_rallyAPIMinor": "0",
                "_ref": "/slm/webservice/v2.0/HierarchicalRequirement/34806108/Attachments",
                "_type": "Attachment",
                "Count": 0
            },
            "Package": null,
            "AcceptedDate": "2016-10-18T23:04:32.234Z",
            "Blocked": false,
            "BlockedReason": null,
            "Blocker": null,
            "Children":             {
                "_rallyAPIMajor": "2",
                "_rallyAPIMinor": "0",
                "_ref": "/slm/webservice/v2.0/HierarchicalRequirement/34806108/Children",
                "_type": "HierarchicalRequirement",
                "Count": 0
            },
            "DefectStatus": "NONE",
            "Defects":             {
                "_rallyAPIMajor": "2",
                "_rallyAPIMinor": "0",
                "_ref": "/slm/webservice/v2.0/HierarchicalRequirement/34806108/Defects",
                "_type": "Defect",
                "Count": 0
            },
            "DirectChildrenCount": 0,
            "DragAndDropRank": "P!!VMgO~~~~~~~~~~~~~~~~~~~~~~~~~~~~~~~~~~~~~~~~~~~~~~~~~~~~~~~~~",
            "HasParent": true,
            "InProgressDate": "2016-09-19T15:13:24.855Z",
            "Iteration":             {
                "_rallyAPIMajor": "2",
                "_rallyAPIMinor": "0",
                "_ref": "/slm/webservice/v2.0/iteration/34443036",
                "_refObjectUUID": "735882a9-78ab-4096-afa8-71ae1ee93cd0",
                "_refObjectName": "Sprint 12",
                "_type": "Iteration"
            },
            "Parent":             {
                "_rallyAPIMajor": "2",
                "_rallyAPIMinor": "0",
                "_ref": "/slm/webservice/v2.0/hierarchicalrequirement/34294911",
                "_refObjectUUID": "5f75d092-a0e4-4494-802f-7abc1f6d17b8",
                "_refObjectName": "Feature: Generate Report",
                "_type": "HierarchicalRequirement"
            },
            "PlanEstimate": 5,
            "Predecessors":             {
                "_rallyAPIMajor": "2",
                "_rallyAPIMinor": "0",
                "_ref": "/slm/webservice/v2.0/HierarchicalRequirement/34806108/Predecessors",
                "_type": "HierarchicalRequirement",
                "Count": 0
            },
            "Recycled": false,
            "Release":             {
                "_rallyAPIMajor": "2",
                "_rallyAPIMinor": "0",
                "_ref": "/slm/webservice/v2.0/release/34571699",
                "_refObjectUUID": "eacfc27a-ff91-484b-bd7a-45c752f3415d",
                "_refObjectName": "Release 2 Production",
                "_type": "Release"
            },
            "Successors":             {
                "_rallyAPIMajor": "2",
                "_rallyAPIMinor": "0",
                "_ref": "/slm/webservice/v2.0/HierarchicalRequirement/34806108/Successors",
                "_type": "HierarchicalRequirement",
                "Count": 0
            },
            "TaskActualTotal": 4.25,
            "TaskEstimateTotal": 7,
            "TaskRemainingTotal": 0,
            "TaskStatus": "COMPLETED",
            "Tasks":             {
                "_rallyAPIMajor": "2",
                "_rallyAPIMinor": "0",
                "_ref": "/slm/webservice/v2.0/HierarchicalRequirement/34806108/Tasks",
                "_type": "Task",
                "Count": 3
            },
            "TestCaseStatus": "NONE",
            "TestCases":             {
                "_rallyAPIMajor": "2",
                "_rallyAPIMinor": "0",
                "_ref": "/slm/webservice/v2.0/HierarchicalRequirement/34806108/TestCases",
                "_type": "TestCase",
                "Count": 0
            },
            "c_ACv4ReqID": null,
            "c_AISRequirementID": null,
            "c_ANTReqID": null,
            "c_BizValue": null,
            "c_CAPTSReqID": null,
            "c_COTSAISReqID": null,
            "c_CromaReqID": null,
            "c_EBinderReqID": null,
            "c_EcBinderReqID": null,
            "c_ETSCReqID": null,
            "Feature": null,
            "c_FRACASReqID": null,
            "c_HRRAReqID": null,
            "c_ITRRReqID": null,
            "c_MsfReqID": null,
            "c_NBIDCReqID": null,
            "c_NFDEReqID": null,
            "c_PARTSReqID": null,
            "c_PMRTReqID": null,
            "c_POAcceptanceCriteria": null,
            "PortfolioItem": null,
            "c_QCAttachments": null,
            "c_QCReqID": null,
            "c_QES2ReqID": null,
            "c_QES2ReqIDDELETED": null,
            "c_Qt2ReqID": null,
            "c_QT3ReqID": null,
            "c_RaMPReqID": null,
            "c_RfutureReqID": null,
            "c_RgemsReqID": null,
            "c_RISCATSReqID": null,
            "c_RLabsReqID": null,
            "c_SABSSReqID": null,
            "c_SabssReqIddelete": null,
            "c_SOCRReqID": null,
            "c_SRDReqID": null,
            "c_SUPSRSRqmtID": null,
            "c_SysReqID": null,
            "c_TandCReqIDCOTS": null,
            "c_TermsandConditionsReqID": null,
            "c_TripodReqID": null,
            "_type": "HierarchicalRequirement"
        }
    ]
}}